{"cameraMode":{"drawMode":0,"name":"Shaded","section":"Shading Mode"},"sceneLighting":true,"audioPlay":false,"sceneViewState":{"showFog":true,"showMaterialUpdate":false,"showSkybox":true,"showFlares":true,"showImageEffects":true,"showParticleSystems":true},"in2DMode":false,"pivot":{"x":406.6841125488281,"y":127.98834228515625,"z":161.5457763671875},"rotation":{"x":0.3145255744457245,"y":-0.1022544577717781,"z":0.034100692719221118,"w":0.9431143999099731},"size":2104.1015625,"orthographic":false}