{"cameraMode":{"drawMode":0,"name":"Shaded","section":"Shading Mode"},"sceneLighting":true,"audioPlay":false,"sceneViewState":{"showFog":true,"showMaterialUpdate":false,"showSkybox":true,"showFlares":true,"showImageEffects":true,"showParticleSystems":true},"in2DMode":false,"pivot":{"x":-7.067409515380859,"y":-1.1225337982177735,"z":7.863212585449219},"rotation":{"x":-0.09150482714176178,"y":0.8959778547286987,"z":-0.2181306630373001,"w":-0.37585869431495669},"size":26.546588897705079,"orthographic":false}